django_twilio_call/__init__.py
django_twilio_call/admin.py
django_twilio_call/apps.py
django_twilio_call/cache.py
django_twilio_call/celery.py
django_twilio_call/conf.py
django_twilio_call/constants.py
django_twilio_call/error_handling.py
django_twilio_call/exceptions.py
django_twilio_call/health.py
django_twilio_call/managers.py
django_twilio_call/mixins.py
django_twilio_call/models.py
django_twilio_call/monitoring.py
django_twilio_call/permissions.py
django_twilio_call/security.py
django_twilio_call/serializers.py
django_twilio_call/settings.py
django_twilio_call/swagger.py
django_twilio_call/tasks.py
django_twilio_call/urls.py
django_twilio_call/views.py
django_twilio_call/management/__init__.py
django_twilio_call/management/commands/__init__.py
django_twilio_call/management/commands/monitor_alerts.py
django_twilio_call/management/commands/monitor_system.py
django_twilio_call/management/commands/monitor_tasks.py
django_twilio_call/migrations/0001_initial.py
django_twilio_call/migrations/__init__.py
django_twilio_call/observability/__init__.py
django_twilio_call/observability/apps.py
django_twilio_call/observability/config.py
django_twilio_call/observability/integration.py
django_twilio_call/observability/urls.py
django_twilio_call/observability/alerts/__init__.py
django_twilio_call/observability/alerts/manager.py
django_twilio_call/observability/cli/__init__.py
django_twilio_call/observability/dashboards/__init__.py
django_twilio_call/observability/dashboards/grafana_dashboards.json
django_twilio_call/observability/dashboards/prometheus_exporter.py
django_twilio_call/observability/dashboards/urls.py
django_twilio_call/observability/health/__init__.py
django_twilio_call/observability/health/checks.py
django_twilio_call/observability/health/urls.py
django_twilio_call/observability/health/views.py
django_twilio_call/observability/logging/__init__.py
django_twilio_call/observability/logging/formatters.py
django_twilio_call/observability/metrics/__init__.py
django_twilio_call-0.1.9.dist-info/licenses/LICENSE
django_twilio_call-0.1.9.dist-info/METADATA
django_twilio_call-0.1.9.dist-info/WHEEL
django_twilio_call-0.1.9.dist-info/top_level.txt
django_twilio_call-0.1.9.dist-info/RECORD
