Metadata-Version: 2.4
Name: django-twilio-call
Version: 0.1.9
Summary: A Django package for call center functionality using Twilio
Home-page: https://github.com/hmesfin/django-twilio-call
Author: Gojjo Tech
Author-email: Gojjo Tech <admin@gojjotech.com>
License: MIT
Project-URL: Homepage, https://github.com/hmesfin/django-twilio-call
Project-URL: Documentation, https://django-twilio-call.readthedocs.io
Project-URL: Repository, https://github.com/hmesfin/django-twilio-call
Project-URL: Bug Tracker, https://github.com/hmesfin/django-twilio-call/issues
Classifier: Development Status :: 4 - Beta
Classifier: Intended Audience :: Developers
Classifier: License :: OSI Approved :: MIT License
Classifier: Operating System :: OS Independent
Classifier: Programming Language :: Python :: 3
Classifier: Framework :: Django
Requires-Python: >=3.8
License-File: LICENSE
Requires-Dist: Django<5.2,>=4.2
Requires-Dist: djangorestframework>=3.14.0
Requires-Dist: twilio>=8.0.0
Requires-Dist: celery>=5.3.0
Requires-Dist: redis>=4.5.0
Requires-Dist: python-decouple>=3.8
Provides-Extra: dev
Requires-Dist: ruff>=0.1.0; extra == "dev"
Requires-Dist: pytest>=7.4.0; extra == "dev"
Requires-Dist: pytest-django>=4.5.0; extra == "dev"
Requires-Dist: pytest-cov>=4.1.0; extra == "dev"
Requires-Dist: factory-boy>=3.3.0; extra == "dev"
Requires-Dist: responses>=0.23.0; extra == "dev"
Requires-Dist: ipython>=8.0.0; extra == "dev"
Provides-Extra: docs
Requires-Dist: sphinx>=7.0.0; extra == "docs"
Requires-Dist: sphinx-rtd-theme>=1.3.0; extra == "docs"
Dynamic: author
Dynamic: home-page
Dynamic: license-file
Dynamic: requires-python
